slurmtui/__init__.py
slurmtui/_version.py
slurmtui/main.py
slurmtui/slurm_utils.py
slurmtui/utils.py
slurmtui/css/slurmtui.css
slurmtui/screens/__init__.py
slurmtui/screens/confirm.py
slurmtui/screens/info.py
slurmtui/screens/old_jobs.py
slurmtui/screens/settings.py
slurmtui/screens/utils.py
slurmtui-0.4.1.dist-info/licenses/LICENSE
slurmtui-0.4.1.dist-info/METADATA
slurmtui-0.4.1.dist-info/WHEEL
slurmtui-0.4.1.dist-info/entry_points.txt
slurmtui-0.4.1.dist-info/top_level.txt
slurmtui-0.4.1.dist-info/RECORD
